fastapi_throttling/__init__.py
fastapi_throttling/throttle.py
fastapi_throttling-0.1.9.dist-info/LICENSE
fastapi_throttling-0.1.9.dist-info/METADATA
fastapi_throttling-0.1.9.dist-info/WHEEL
fastapi_throttling-0.1.9.dist-info/RECORD
