Metadata-Version: 2.1
Name: fastapi-throttling
Version: 0.1.9
Summary: Limit amount of requests to your FastAPI.
License: GPLv2
Author: wwnbb
Author-email: wwnbb1@gmail.com
Requires-Python: >=3.11.4,<4.0.0
Classifier: License :: Other/Proprietary License
Classifier: Programming Language :: Python :: 3
Requires-Dist: fastapi (>=0.96.0,<0.97.0)
Requires-Dist: redis (>=4.5.0,<5.0.0)
